{

    "Broadview"
:
    "10",
        "Haller Lake"
:
    "21",
        "Pinehurst"
:
    "16",
        "Olympic Hills"
:
    "2",
        "Cedar Park"
:
    "4",
        "Greenwood"
:
    "10",
        "Maple Leaf"
:
    "10",
        "Wedgwood"
:
    "24",
        "Sand Point"
:
    "10",
        "Greenlake"
:
    "27",
        "Ballard"
:
    "20",
        "Fremont"
:
    "22",
        "University District"
:
    "43",
        "Laurelhurst"
:
    "18",
        "Magnolia"
:
    "22",
        "Queen Anne"
:
    "25",
        "Lower Queen Anne"
:
    "22",
        "Capitol Hill"
:
    "15",
        "Downtown"
:
    "2",
        "Montlake"
:
    "20",
        "Broadmoor"
:
    "7",
        "Madison Park"
:
    "20",
        "Magnolia"
:
    "22",
        "Queen Anne"
:
    "25",
        "Arbor Heights"
:
    "4",
        "Fauntleroy"
:
    "9",
        "West Seattle"
:
    "22",
        "Alki"
:
    "4",
        "Admiral"
:
    "1",
        "Industrial District"
:
    "12",
        "North Delridge"
:
    "5",
        "Riverview"
:
    "6",
        "Highland Park"
:
    "16",
        "Georgetown"
:
    "15",
        "Beacon Hill"
:
    "13",
        "Rainer Beach"
:
    "9",
        "Steward Park"
:
    "16",
        "Brighton"
:
    "5",
        "Columbia City"
:
    "4",
        "Mount Baker"
:
    "5",
        "Altantic"
:
    "5",
        "Leschi"
:
    "4",
        "Madrona"
:
    "10",
        "Central District"
:
    "9",
        "Madison Park"
:
    "20",
        "Broadmoore"
:
    "7",
        "Montlake"
:
    "20",
        "Capital Hill"
:
    "15",
        "Downtown"
:
    "2",
        "Lower Queen Anne"
:
    "22"
}
